[
    {
        "Age group": "0-30 days",
        "Number of subjects": 15,
        "Geometric mean ± SD": "37 ± 17",
        "Min-max": "18-78",
        "95% confidence intervals": ["31", "50"]
    },
    {
        "Age group": "1-5 months",
        "Number of subjects": 10,
        "Geometric mean ± SD": "24 ± 12",
        "Min-max": "13-53",
        "95% confidence intervals": ["17", "35"]
    },
    {
        "Age group": "6-8 months",
        "Number of subjects": 14,
        "Geometric mean ± SD": "35 ± 25",
        "Min-max": "14-100",
        "95% confidence intervals": ["27", "56"]
    },
    {
        "Age group": "9-12 months",
        "Number of subjects": 29,
        "Geometric mean ± SD": "38 ± 24",
        "Min-max": "18-110",
        "95% confidence intervals": ["34", "53"]
    },
    {
        "Age group": "13-24 months",
        "Number of subjects": 65,
        "Geometric mean ± SD": "37 ± 25",
        "Min-max": "16-132",
        "95% confidence intervals": ["37", "49"]
    },
    {
        "Age group": "25-36 months",
        "Number of subjects": 54,
        "Geometric mean ± SD": "32 ± 21",
        "Min-max": "14-125",
        "95% confidence intervals": ["30", "42"]
    },
    {
        "Age group": "37-48 months",
        "Number of subjects": 45,
        "Geometric mean ± SD": "37 ± 25",
        "Min-max": "15-120",
        "95% confidence intervals": ["35", "50"]
    },
    {
        "Age group": "49-72 months",
        "Number of subjects": 54,
        "Geometric mean ± SD": "37 ± 20",
        "Min-max": "15-107",
        "95% confidence intervals": ["36", "47"]
    },
    {
        "Age group": "7-8 years",
        "Number of subjects": 62,
        "Geometric mean ± SD": "51 ± 43",
        "Min-max": "21-186",
        "95% confidence intervals": ["51", "73"]
    },
    {
        "Age group": "9-10 years",
        "Number of subjects": 65,
        "Geometric mean ± SD": "51 ± 34",
        "Min-max": "20-186",
        "95% confidence intervals": ["50", "67"]
    },
    {
        "Age group": "11-12 years",
        "Number of subjects": 34,
        "Geometric mean ± SD": "53 ± 40",
        "Min-max": "29-200",
        "95% confidence intervals": ["47", "75"]
    },
    {
        "Age group": "13-14 years",
        "Number of subjects": 29,
        "Geometric mean ± SD": "80 ± 56",
        "Min-max": "28-223",
        "95% confidence intervals": ["73", "117"]
    },
    {
        "Age group": "15-16 years",
        "Number of subjects": 18,
        "Geometric mean ± SD": "58 ± 21",
        "Min-max": "30-120",
        "95% confidence intervals": ["51", "73"]
    },
    {
        "Age group": "Older than 16 years",
        "Number of subjects": 21,
        "Geometric mean ± SD": "50 ± 33",
        "Min-max": "21-152",
        "95% confidence intervals": ["43", "73"]
    }
]
